shunkei_sdk/__init__.py
shunkei_sdk/find_shunkei.py
shunkei_sdk/webrtc.py
shunkei_sdk-0.2.1.dist-info/LICENSE
shunkei_sdk-0.2.1.dist-info/METADATA
shunkei_sdk-0.2.1.dist-info/WHEEL
shunkei_sdk-0.2.1.dist-info/top_level.txt
shunkei_sdk-0.2.1.dist-info/RECORD
